di/__init__.py
dimax-0.0.0.dist-info/LICENSE
dimax-0.0.0.dist-info/METADATA
dimax-0.0.0.dist-info/WHEEL
dimax-0.0.0.dist-info/top_level.txt
dimax-0.0.0.dist-info/RECORD
