Metadata-Version: 2.1
Name: dimax
Version: 0.0.0
Summary: A powerful dependency injection framework that automatically injects objects, promoting loose coupling, improving testability, and centralizing configuration for easier maintenance.
Author: Mateusz Baran
Maintainer: Mateusz Baran
License: MIT License
Project-URL: repository, https://github.com/mateuszbaransanok/dimax
Keywords: Dependency Injection
Classifier: Development Status :: 4 - Beta
Classifier: Programming Language :: Python
Classifier: Programming Language :: Python :: 3
Classifier: Programming Language :: Python :: 3 :: Only
Classifier: Programming Language :: Python :: 3.10
Classifier: Operating System :: OS Independent
Classifier: License :: OSI Approved :: MIT License
Requires-Python: >=3.10
License-File: LICENSE
Provides-Extra: test
Requires-Dist: Flake8-pyproject ==1.2.3 ; extra == 'test'
Requires-Dist: black ==24.3.0 ; extra == 'test'
Requires-Dist: flake8 ==7.0.0 ; extra == 'test'
Requires-Dist: isort ==5.13.2 ; extra == 'test'
Requires-Dist: mypy ==1.9.0 ; extra == 'test'
Requires-Dist: pytest-asyncio ==0.23.7 ; extra == 'test'
Requires-Dist: pytest ==8.1.1 ; extra == 'test'
